otel_log_grpc_handler/__init__.py
otel_log_grpc_handler/handler.py
otel_log_grpc_handler-0.1.1.dist-info/licenses/LICENSE
tests/conftest.py
tests/test_handler.py
tests/test_integration.py
otel_log_grpc_handler-0.1.1.dist-info/METADATA
otel_log_grpc_handler-0.1.1.dist-info/WHEEL
otel_log_grpc_handler-0.1.1.dist-info/top_level.txt
otel_log_grpc_handler-0.1.1.dist-info/RECORD
