Metadata-Version: 2.4
Name: otel-log-grpc-handler
Version: 0.1.1
Summary: A Python logging handler that sends logs to an OpenTelemetry OTLP collector via gRPC, with optional automatic LogRecord mapping.
Author-email: Andrey Ilyin <jemmix@gmail.com>
License-Expression: MIT
Project-URL: Homepage, https://github.com/jemmix/otel-log-grpc-handler
Project-URL: Bug Tracker, https://github.com/jemmix/otel-log-grpc-handler/issues
Keywords: opentelemetry,logging,otel,grpc,exporter,handler,logs
Classifier: Programming Language :: Python :: 3
Classifier: Operating System :: OS Independent
Classifier: Topic :: System :: Logging
Classifier: Framework :: OpenTelemetry
Requires-Python: >=3.9
License-File: LICENSE
Requires-Dist: grpcio>=1.59.0
Requires-Dist: opentelemetry-proto>=1.34.1
Provides-Extra: mapper
Requires-Dist: otel-log-proto-mapper>=0.1.4; extra == "mapper"
Provides-Extra: test
Requires-Dist: pytest>=8.4.0; extra == "test"
Requires-Dist: otel-log-proto-mapper>=0.1.4; extra == "test"
Dynamic: license-file
